{"Database Schema & Initial Setup Complete": 2, "Core ML Models Integrated": 3, "NLP Pipeline Working": 4, "Backend API & Processing Complete": 5, "Complete System Integration & Testing": 6, "1.1 Finalize and Implement the Email Database": 7, "1.2 Dataset Processing System": 8, "2.1 Email Category Classification System": 9, "2.2 Named Entity Recognition Integration": 10, "2.3 Emotion & Tone Detection": 11, "3.1 Summarization Engine": 12, "3.2 Smart Reply Generator": 13, "4.1 Modular Pipeline & Logic System": 14, "4.2 REST API for Predictions": 15, "5.1 Interface Design & Tagging": 16, "5.2 GUI Logic & Integration": 17, "5.3 Smart User Interactions": 18}